F1_2021_Telemetry/__init__.py
F1_2021_Telemetry/defs.py
F1_2021_Telemetry/packets.py
F1_2021_Telemetry/telemetry.py
F1_2021_Telemetry/translate.py
F1_2021_Telemetry/utils.py
f1_2021_telemetry-0.1.dist-info/METADATA
f1_2021_telemetry-0.1.dist-info/WHEEL
f1_2021_telemetry-0.1.dist-info/licenses/LICENSE
f1_2021_telemetry-0.1.dist-info/RECORD
