Metadata-Version: 2.1
Name: F1_2021_Telemetry
Version: 0.1
Summary: A python package to parse telemetry data from the F1 game into python objects
Project-URL: Homepage, https://github.com/TeddyWoodburn/F1_Game_Telemetry
Project-URL: Bug Tracker, https://github.com/TeddyWoodburn/F1_Game_Telemetry/issues
License-File: LICENSE
Classifier: License :: OSI Approved :: MIT License
Classifier: Operating System :: OS Independent
Classifier: Programming Language :: Python :: 3
Requires-Python: >=3.10
